{
  "options": {
    "proxy": "http://aeldreportalen.syddjurs.test"
  },
  "javascripts": [
    "src/vendor/bootstrap/dist/js/bootstrap.js",
    "src/js/bs3-designer.js",
    "src/js/bs3-sidebar.js",
    "src/vendor/jquery-placeholder/jquery.placeholder.js",
    "src/vendor/jquery.cookie/jquery.cookie.js",
    "src/vendor/fastclick/lib/fastclick.js",
    "src/js/init.js"
  ],
  "styles": [
    "src/less/stylesheet.less"
  ],
  "fonts": [
    "src/vendor/fontawesome/fonts/*",
    "src/vendor/bootstrap/fonts/glyphicons-halflings-regular.*"
  ]
}
